tabletree/__init__.py
tabletree/tabletree.py
tabletree/__pycache__/__init__.cpython-37.pyc
tabletree/__pycache__/tabletree.cpython-37.pyc
tabletree-0.3.2.dist-info/AUTHORS.rst
tabletree-0.3.2.dist-info/LICENSE
tabletree-0.3.2.dist-info/METADATA
tabletree-0.3.2.dist-info/WHEEL
tabletree-0.3.2.dist-info/top_level.txt
tabletree-0.3.2.dist-info/RECORD
