Metadata-Version: 2.1
Name: tabletree
Version: 0.3.2
Summary: Python package for exploring and linking multiple SQL-like tables
Home-page: https://github.com/rluo/tabletree
Author: Xi Rossi LUO
Author-email: xi.rossi.luo@gmail.com
License: GPL v3
Platform: any
Classifier: Development Status :: 4 - Beta
Classifier: Programming Language :: Python
Requires-Python: >=3.4
Requires-Dist: numpy
Requires-Dist: pandas
Provides-Extra: testing
Requires-Dist: pytest ; extra == 'testing'
Requires-Dist: pytest-cov ; extra == 'testing'
